easygram/__init__.py
easygram/api.py
easygram/bot.py
ezygram-0.2.dist-info/METADATA
ezygram-0.2.dist-info/WHEEL
ezygram-0.2.dist-info/top_level.txt
ezygram-0.2.dist-info/RECORD
