Metadata-Version: 2.4
Name: ezygram
Version: 0.2
Summary: Super simple Telegram Bot API
License: MIT
Requires-Python: >=3.8
Requires-Dist: requests
